createActiveTask2List/__init__.py
createActiveTask2List/createActiveTask2List.py
createActiveTask2List-1.1.1.dist-info/LICENSE
createActiveTask2List-1.1.1.dist-info/METADATA
createActiveTask2List-1.1.1.dist-info/WHEEL
createActiveTask2List-1.1.1.dist-info/top_level.txt
createActiveTask2List-1.1.1.dist-info/RECORD
